package com.google.android.gms.nearby.sharing.internal;

import android.os.IBinder;
import android.os.Parcel;

class zza$zza$zza
  implements zza
{
  private IBinder zzoz;
  
  zza$zza$zza(IBinder paramIBinder)
  {
    zzoz = paramIBinder;
  }
  
  public IBinder asBinder()
  {
    return zzoz;
  }
  
  /* Error */
  public void zza(com.google.android.gms.nearby.sharing.AppContentReceivedResult paramAppContentReceivedResult)
  {
    // Byte code:
    //   0: invokestatic 26	android/os/Parcel:obtain	()Landroid/os/Parcel;
    //   3: astore_2
    //   4: aload_2
    //   5: ldc 28
    //   7: invokevirtual 32	android/os/Parcel:writeInterfaceToken	(Ljava/lang/String;)V
    //   10: aload_1
    //   11: ifnull +33 -> 44
    //   14: aload_2
    //   15: iconst_1
    //   16: invokevirtual 36	android/os/Parcel:writeInt	(I)V
    //   19: aload_1
    //   20: aload_2
    //   21: iconst_0
    //   22: invokevirtual 42	com/google/android/gms/nearby/sharing/AppContentReceivedResult:writeToParcel	(Landroid/os/Parcel;I)V
    //   25: aload_0
    //   26: getfield 15	com/google/android/gms/nearby/sharing/internal/zza$zza$zza:zzoz	Landroid/os/IBinder;
    //   29: iconst_2
    //   30: aload_2
    //   31: aconst_null
    //   32: iconst_1
    //   33: invokeinterface 48 5 0
    //   38: pop
    //   39: aload_2
    //   40: invokevirtual 51	android/os/Parcel:recycle	()V
    //   43: return
    //   44: aload_2
    //   45: iconst_0
    //   46: invokevirtual 36	android/os/Parcel:writeInt	(I)V
    //   49: goto -24 -> 25
    //   52: astore_1
    //   53: aload_2
    //   54: invokevirtual 51	android/os/Parcel:recycle	()V
    //   57: aload_1
    //   58: athrow
    // Local variable table:
    //   start	length	slot	name	signature
    //   0	59	0	this	zza
    //   0	59	1	paramAppContentReceivedResult	com.google.android.gms.nearby.sharing.AppContentReceivedResult
    //   3	51	2	localParcel	Parcel
    // Exception table:
    //   from	to	target	type
    //   4	10	52	finally
    //   14	25	52	finally
    //   25	39	52	finally
    //   44	49	52	finally
  }
  
  public String zzfC(String paramString)
  {
    Parcel localParcel1 = Parcel.obtain();
    Parcel localParcel2 = Parcel.obtain();
    try
    {
      localParcel1.writeInterfaceToken("com.google.android.gms.nearby.sharing.internal.IAppContentReceiver");
      localParcel1.writeString(paramString);
      zzoz.transact(1, localParcel1, localParcel2, 0);
      localParcel2.readException();
      paramString = localParcel2.readString();
      return paramString;
    }
    finally
    {
      localParcel2.recycle();
      localParcel1.recycle();
    }
  }
}

/* Location:
 * Qualified Name:     com.google.android.gms.nearby.sharing.internal.zza.zza.zza
 * Java Class Version: 6 (50.0)
 * JD-Core Version:    0.7.1
 */