package com.google.android.gms.internal;

import android.os.IBinder;
import android.os.Parcel;

class zzez$zza$zza
  implements zzez
{
  private IBinder zzoz;
  
  zzez$zza$zza(IBinder paramIBinder)
  {
    zzoz = paramIBinder;
  }
  
  public IBinder asBinder()
  {
    return zzoz;
  }
  
  public void onAdClicked()
  {
    Parcel localParcel1 = Parcel.obtain();
    Parcel localParcel2 = Parcel.obtain();
    try
    {
      localParcel1.writeInterfaceToken("com.google.android.gms.ads.internal.mediation.client.IMediationAdapterListener");
      zzoz.transact(1, localParcel1, localParcel2, 0);
      localParcel2.readException();
      return;
    }
    finally
    {
      localParcel2.recycle();
      localParcel1.recycle();
    }
  }
  
  public void onAdClosed()
  {
    Parcel localParcel1 = Parcel.obtain();
    Parcel localParcel2 = Parcel.obtain();
    try
    {
      localParcel1.writeInterfaceToken("com.google.android.gms.ads.internal.mediation.client.IMediationAdapterListener");
      zzoz.transact(2, localParcel1, localParcel2, 0);
      localParcel2.readException();
      return;
    }
    finally
    {
      localParcel2.recycle();
      localParcel1.recycle();
    }
  }
  
  public void onAdFailedToLoad(int paramInt)
  {
    Parcel localParcel1 = Parcel.obtain();
    Parcel localParcel2 = Parcel.obtain();
    try
    {
      localParcel1.writeInterfaceToken("com.google.android.gms.ads.internal.mediation.client.IMediationAdapterListener");
      localParcel1.writeInt(paramInt);
      zzoz.transact(3, localParcel1, localParcel2, 0);
      localParcel2.readException();
      return;
    }
    finally
    {
      localParcel2.recycle();
      localParcel1.recycle();
    }
  }
  
  public void onAdLeftApplication()
  {
    Parcel localParcel1 = Parcel.obtain();
    Parcel localParcel2 = Parcel.obtain();
    try
    {
      localParcel1.writeInterfaceToken("com.google.android.gms.ads.internal.mediation.client.IMediationAdapterListener");
      zzoz.transact(4, localParcel1, localParcel2, 0);
      localParcel2.readException();
      return;
    }
    finally
    {
      localParcel2.recycle();
      localParcel1.recycle();
    }
  }
  
  public void onAdLoaded()
  {
    Parcel localParcel1 = Parcel.obtain();
    Parcel localParcel2 = Parcel.obtain();
    try
    {
      localParcel1.writeInterfaceToken("com.google.android.gms.ads.internal.mediation.client.IMediationAdapterListener");
      zzoz.transact(6, localParcel1, localParcel2, 0);
      localParcel2.readException();
      return;
    }
    finally
    {
      localParcel2.recycle();
      localParcel1.recycle();
    }
  }
  
  public void onAdOpened()
  {
    Parcel localParcel1 = Parcel.obtain();
    Parcel localParcel2 = Parcel.obtain();
    try
    {
      localParcel1.writeInterfaceToken("com.google.android.gms.ads.internal.mediation.client.IMediationAdapterListener");
      zzoz.transact(5, localParcel1, localParcel2, 0);
      localParcel2.readException();
      return;
    }
    finally
    {
      localParcel2.recycle();
      localParcel1.recycle();
    }
  }
  
  /* Error */
  public void zza(zzfa paramzzfa)
  {
    // Byte code:
    //   0: invokestatic 25	android/os/Parcel:obtain	()Landroid/os/Parcel;
    //   3: astore_2
    //   4: invokestatic 25	android/os/Parcel:obtain	()Landroid/os/Parcel;
    //   7: astore_3
    //   8: aload_2
    //   9: ldc 27
    //   11: invokevirtual 31	android/os/Parcel:writeInterfaceToken	(Ljava/lang/String;)V
    //   14: aload_1
    //   15: ifnull +43 -> 58
    //   18: aload_1
    //   19: invokeinterface 58 1 0
    //   24: astore_1
    //   25: aload_2
    //   26: aload_1
    //   27: invokevirtual 61	android/os/Parcel:writeStrongBinder	(Landroid/os/IBinder;)V
    //   30: aload_0
    //   31: getfield 15	com/google/android/gms/internal/zzez$zza$zza:zzoz	Landroid/os/IBinder;
    //   34: bipush 7
    //   36: aload_2
    //   37: aload_3
    //   38: iconst_0
    //   39: invokeinterface 37 5 0
    //   44: pop
    //   45: aload_3
    //   46: invokevirtual 40	android/os/Parcel:readException	()V
    //   49: aload_3
    //   50: invokevirtual 43	android/os/Parcel:recycle	()V
    //   53: aload_2
    //   54: invokevirtual 43	android/os/Parcel:recycle	()V
    //   57: return
    //   58: aconst_null
    //   59: astore_1
    //   60: goto -35 -> 25
    //   63: astore_1
    //   64: aload_3
    //   65: invokevirtual 43	android/os/Parcel:recycle	()V
    //   68: aload_2
    //   69: invokevirtual 43	android/os/Parcel:recycle	()V
    //   72: aload_1
    //   73: athrow
    // Local variable table:
    //   start	length	slot	name	signature
    //   0	74	0	this	zza
    //   0	74	1	paramzzfa	zzfa
    //   3	66	2	localParcel1	Parcel
    //   7	58	3	localParcel2	Parcel
    // Exception table:
    //   from	to	target	type
    //   8	14	63	finally
    //   18	25	63	finally
    //   25	49	63	finally
  }
}

/* Location:
 * Qualified Name:     com.google.android.gms.internal.zzez.zza.zza
 * Java Class Version: 6 (50.0)
 * JD-Core Version:    0.7.1
 */