package com.google.android.gms.internal;

import android.os.IBinder;

class zzkp$zza$zza
  implements zzkp
{
  private IBinder zzoz;
  
  zzkp$zza$zza(IBinder paramIBinder)
  {
    zzoz = paramIBinder;
  }
  
  public IBinder asBinder()
  {
    return zzoz;
  }
  
  /* Error */
  public void zza(zzko paramzzko)
  {
    // Byte code:
    //   0: invokestatic 26	android/os/Parcel:obtain	()Landroid/os/Parcel;
    //   3: astore_2
    //   4: invokestatic 26	android/os/Parcel:obtain	()Landroid/os/Parcel;
    //   7: astore_3
    //   8: aload_2
    //   9: ldc 28
    //   11: invokevirtual 32	android/os/Parcel:writeInterfaceToken	(Ljava/lang/String;)V
    //   14: aload_1
    //   15: ifnull +42 -> 57
    //   18: aload_1
    //   19: invokeinterface 36 1 0
    //   24: astore_1
    //   25: aload_2
    //   26: aload_1
    //   27: invokevirtual 39	android/os/Parcel:writeStrongBinder	(Landroid/os/IBinder;)V
    //   30: aload_0
    //   31: getfield 15	com/google/android/gms/internal/zzkp$zza$zza:zzoz	Landroid/os/IBinder;
    //   34: iconst_3
    //   35: aload_2
    //   36: aload_3
    //   37: iconst_0
    //   38: invokeinterface 45 5 0
    //   43: pop
    //   44: aload_3
    //   45: invokevirtual 48	android/os/Parcel:readException	()V
    //   48: aload_3
    //   49: invokevirtual 51	android/os/Parcel:recycle	()V
    //   52: aload_2
    //   53: invokevirtual 51	android/os/Parcel:recycle	()V
    //   56: return
    //   57: aconst_null
    //   58: astore_1
    //   59: goto -34 -> 25
    //   62: astore_1
    //   63: aload_3
    //   64: invokevirtual 51	android/os/Parcel:recycle	()V
    //   67: aload_2
    //   68: invokevirtual 51	android/os/Parcel:recycle	()V
    //   71: aload_1
    //   72: athrow
    // Local variable table:
    //   start	length	slot	name	signature
    //   0	73	0	this	zza
    //   0	73	1	paramzzko	zzko
    //   3	65	2	localParcel1	android.os.Parcel
    //   7	57	3	localParcel2	android.os.Parcel
    // Exception table:
    //   from	to	target	type
    //   8	14	62	finally
    //   18	25	62	finally
    //   25	48	62	finally
  }
  
  /* Error */
  public void zza(zzko paramzzko, String paramString)
  {
    // Byte code:
    //   0: invokestatic 26	android/os/Parcel:obtain	()Landroid/os/Parcel;
    //   3: astore_3
    //   4: invokestatic 26	android/os/Parcel:obtain	()Landroid/os/Parcel;
    //   7: astore 4
    //   9: aload_3
    //   10: ldc 28
    //   12: invokevirtual 32	android/os/Parcel:writeInterfaceToken	(Ljava/lang/String;)V
    //   15: aload_1
    //   16: ifnull +50 -> 66
    //   19: aload_1
    //   20: invokeinterface 36 1 0
    //   25: astore_1
    //   26: aload_3
    //   27: aload_1
    //   28: invokevirtual 39	android/os/Parcel:writeStrongBinder	(Landroid/os/IBinder;)V
    //   31: aload_3
    //   32: aload_2
    //   33: invokevirtual 55	android/os/Parcel:writeString	(Ljava/lang/String;)V
    //   36: aload_0
    //   37: getfield 15	com/google/android/gms/internal/zzkp$zza$zza:zzoz	Landroid/os/IBinder;
    //   40: iconst_2
    //   41: aload_3
    //   42: aload 4
    //   44: iconst_0
    //   45: invokeinterface 45 5 0
    //   50: pop
    //   51: aload 4
    //   53: invokevirtual 48	android/os/Parcel:readException	()V
    //   56: aload 4
    //   58: invokevirtual 51	android/os/Parcel:recycle	()V
    //   61: aload_3
    //   62: invokevirtual 51	android/os/Parcel:recycle	()V
    //   65: return
    //   66: aconst_null
    //   67: astore_1
    //   68: goto -42 -> 26
    //   71: astore_1
    //   72: aload 4
    //   74: invokevirtual 51	android/os/Parcel:recycle	()V
    //   77: aload_3
    //   78: invokevirtual 51	android/os/Parcel:recycle	()V
    //   81: aload_1
    //   82: athrow
    // Local variable table:
    //   start	length	slot	name	signature
    //   0	83	0	this	zza
    //   0	83	1	paramzzko	zzko
    //   0	83	2	paramString	String
    //   3	75	3	localParcel1	android.os.Parcel
    //   7	66	4	localParcel2	android.os.Parcel
    // Exception table:
    //   from	to	target	type
    //   9	15	71	finally
    //   19	26	71	finally
    //   26	56	71	finally
  }
  
  /* Error */
  public void zzb(zzko paramzzko, String paramString)
  {
    // Byte code:
    //   0: invokestatic 26	android/os/Parcel:obtain	()Landroid/os/Parcel;
    //   3: astore_3
    //   4: invokestatic 26	android/os/Parcel:obtain	()Landroid/os/Parcel;
    //   7: astore 4
    //   9: aload_3
    //   10: ldc 28
    //   12: invokevirtual 32	android/os/Parcel:writeInterfaceToken	(Ljava/lang/String;)V
    //   15: aload_1
    //   16: ifnull +50 -> 66
    //   19: aload_1
    //   20: invokeinterface 36 1 0
    //   25: astore_1
    //   26: aload_3
    //   27: aload_1
    //   28: invokevirtual 39	android/os/Parcel:writeStrongBinder	(Landroid/os/IBinder;)V
    //   31: aload_3
    //   32: aload_2
    //   33: invokevirtual 55	android/os/Parcel:writeString	(Ljava/lang/String;)V
    //   36: aload_0
    //   37: getfield 15	com/google/android/gms/internal/zzkp$zza$zza:zzoz	Landroid/os/IBinder;
    //   40: iconst_1
    //   41: aload_3
    //   42: aload 4
    //   44: iconst_0
    //   45: invokeinterface 45 5 0
    //   50: pop
    //   51: aload 4
    //   53: invokevirtual 48	android/os/Parcel:readException	()V
    //   56: aload 4
    //   58: invokevirtual 51	android/os/Parcel:recycle	()V
    //   61: aload_3
    //   62: invokevirtual 51	android/os/Parcel:recycle	()V
    //   65: return
    //   66: aconst_null
    //   67: astore_1
    //   68: goto -42 -> 26
    //   71: astore_1
    //   72: aload 4
    //   74: invokevirtual 51	android/os/Parcel:recycle	()V
    //   77: aload_3
    //   78: invokevirtual 51	android/os/Parcel:recycle	()V
    //   81: aload_1
    //   82: athrow
    // Local variable table:
    //   start	length	slot	name	signature
    //   0	83	0	this	zza
    //   0	83	1	paramzzko	zzko
    //   0	83	2	paramString	String
    //   3	75	3	localParcel1	android.os.Parcel
    //   7	66	4	localParcel2	android.os.Parcel
    // Exception table:
    //   from	to	target	type
    //   9	15	71	finally
    //   19	26	71	finally
    //   26	56	71	finally
  }
}

/* Location:
 * Qualified Name:     com.google.android.gms.internal.zzkp.zza.zza
 * Java Class Version: 6 (50.0)
 * JD-Core Version:    0.7.1
 */