package com.google.android.gms.internal;

import android.os.IBinder;

class zzoq$zza$zza
  implements zzoq
{
  private IBinder zzoz;
  
  zzoq$zza$zza(IBinder paramIBinder)
  {
    zzoz = paramIBinder;
  }
  
  public IBinder asBinder()
  {
    return zzoz;
  }
  
  /* Error */
  public void zza(com.google.android.gms.fitness.request.SessionInsertRequest paramSessionInsertRequest)
  {
    // Byte code:
    //   0: invokestatic 26	android/os/Parcel:obtain	()Landroid/os/Parcel;
    //   3: astore_2
    //   4: invokestatic 26	android/os/Parcel:obtain	()Landroid/os/Parcel;
    //   7: astore_3
    //   8: aload_2
    //   9: ldc 28
    //   11: invokevirtual 32	android/os/Parcel:writeInterfaceToken	(Ljava/lang/String;)V
    //   14: aload_1
    //   15: ifnull +41 -> 56
    //   18: aload_2
    //   19: iconst_1
    //   20: invokevirtual 36	android/os/Parcel:writeInt	(I)V
    //   23: aload_1
    //   24: aload_2
    //   25: iconst_0
    //   26: invokevirtual 42	com/google/android/gms/fitness/request/SessionInsertRequest:writeToParcel	(Landroid/os/Parcel;I)V
    //   29: aload_0
    //   30: getfield 15	com/google/android/gms/internal/zzoq$zza$zza:zzoz	Landroid/os/IBinder;
    //   33: iconst_3
    //   34: aload_2
    //   35: aload_3
    //   36: iconst_0
    //   37: invokeinterface 48 5 0
    //   42: pop
    //   43: aload_3
    //   44: invokevirtual 51	android/os/Parcel:readException	()V
    //   47: aload_3
    //   48: invokevirtual 54	android/os/Parcel:recycle	()V
    //   51: aload_2
    //   52: invokevirtual 54	android/os/Parcel:recycle	()V
    //   55: return
    //   56: aload_2
    //   57: iconst_0
    //   58: invokevirtual 36	android/os/Parcel:writeInt	(I)V
    //   61: goto -32 -> 29
    //   64: astore_1
    //   65: aload_3
    //   66: invokevirtual 54	android/os/Parcel:recycle	()V
    //   69: aload_2
    //   70: invokevirtual 54	android/os/Parcel:recycle	()V
    //   73: aload_1
    //   74: athrow
    // Local variable table:
    //   start	length	slot	name	signature
    //   0	75	0	this	zza
    //   0	75	1	paramSessionInsertRequest	com.google.android.gms.fitness.request.SessionInsertRequest
    //   3	67	2	localParcel1	android.os.Parcel
    //   7	59	3	localParcel2	android.os.Parcel
    // Exception table:
    //   from	to	target	type
    //   8	14	64	finally
    //   18	29	64	finally
    //   29	47	64	finally
    //   56	61	64	finally
  }
  
  /* Error */
  public void zza(com.google.android.gms.fitness.request.SessionReadRequest paramSessionReadRequest)
  {
    // Byte code:
    //   0: invokestatic 26	android/os/Parcel:obtain	()Landroid/os/Parcel;
    //   3: astore_2
    //   4: invokestatic 26	android/os/Parcel:obtain	()Landroid/os/Parcel;
    //   7: astore_3
    //   8: aload_2
    //   9: ldc 28
    //   11: invokevirtual 32	android/os/Parcel:writeInterfaceToken	(Ljava/lang/String;)V
    //   14: aload_1
    //   15: ifnull +41 -> 56
    //   18: aload_2
    //   19: iconst_1
    //   20: invokevirtual 36	android/os/Parcel:writeInt	(I)V
    //   23: aload_1
    //   24: aload_2
    //   25: iconst_0
    //   26: invokevirtual 58	com/google/android/gms/fitness/request/SessionReadRequest:writeToParcel	(Landroid/os/Parcel;I)V
    //   29: aload_0
    //   30: getfield 15	com/google/android/gms/internal/zzoq$zza$zza:zzoz	Landroid/os/IBinder;
    //   33: iconst_4
    //   34: aload_2
    //   35: aload_3
    //   36: iconst_0
    //   37: invokeinterface 48 5 0
    //   42: pop
    //   43: aload_3
    //   44: invokevirtual 51	android/os/Parcel:readException	()V
    //   47: aload_3
    //   48: invokevirtual 54	android/os/Parcel:recycle	()V
    //   51: aload_2
    //   52: invokevirtual 54	android/os/Parcel:recycle	()V
    //   55: return
    //   56: aload_2
    //   57: iconst_0
    //   58: invokevirtual 36	android/os/Parcel:writeInt	(I)V
    //   61: goto -32 -> 29
    //   64: astore_1
    //   65: aload_3
    //   66: invokevirtual 54	android/os/Parcel:recycle	()V
    //   69: aload_2
    //   70: invokevirtual 54	android/os/Parcel:recycle	()V
    //   73: aload_1
    //   74: athrow
    // Local variable table:
    //   start	length	slot	name	signature
    //   0	75	0	this	zza
    //   0	75	1	paramSessionReadRequest	com.google.android.gms.fitness.request.SessionReadRequest
    //   3	67	2	localParcel1	android.os.Parcel
    //   7	59	3	localParcel2	android.os.Parcel
    // Exception table:
    //   from	to	target	type
    //   8	14	64	finally
    //   18	29	64	finally
    //   29	47	64	finally
    //   56	61	64	finally
  }
  
  /* Error */
  public void zza(com.google.android.gms.fitness.request.SessionRegistrationRequest paramSessionRegistrationRequest)
  {
    // Byte code:
    //   0: invokestatic 26	android/os/Parcel:obtain	()Landroid/os/Parcel;
    //   3: astore_2
    //   4: invokestatic 26	android/os/Parcel:obtain	()Landroid/os/Parcel;
    //   7: astore_3
    //   8: aload_2
    //   9: ldc 28
    //   11: invokevirtual 32	android/os/Parcel:writeInterfaceToken	(Ljava/lang/String;)V
    //   14: aload_1
    //   15: ifnull +41 -> 56
    //   18: aload_2
    //   19: iconst_1
    //   20: invokevirtual 36	android/os/Parcel:writeInt	(I)V
    //   23: aload_1
    //   24: aload_2
    //   25: iconst_0
    //   26: invokevirtual 62	com/google/android/gms/fitness/request/SessionRegistrationRequest:writeToParcel	(Landroid/os/Parcel;I)V
    //   29: aload_0
    //   30: getfield 15	com/google/android/gms/internal/zzoq$zza$zza:zzoz	Landroid/os/IBinder;
    //   33: iconst_5
    //   34: aload_2
    //   35: aload_3
    //   36: iconst_0
    //   37: invokeinterface 48 5 0
    //   42: pop
    //   43: aload_3
    //   44: invokevirtual 51	android/os/Parcel:readException	()V
    //   47: aload_3
    //   48: invokevirtual 54	android/os/Parcel:recycle	()V
    //   51: aload_2
    //   52: invokevirtual 54	android/os/Parcel:recycle	()V
    //   55: return
    //   56: aload_2
    //   57: iconst_0
    //   58: invokevirtual 36	android/os/Parcel:writeInt	(I)V
    //   61: goto -32 -> 29
    //   64: astore_1
    //   65: aload_3
    //   66: invokevirtual 54	android/os/Parcel:recycle	()V
    //   69: aload_2
    //   70: invokevirtual 54	android/os/Parcel:recycle	()V
    //   73: aload_1
    //   74: athrow
    // Local variable table:
    //   start	length	slot	name	signature
    //   0	75	0	this	zza
    //   0	75	1	paramSessionRegistrationRequest	com.google.android.gms.fitness.request.SessionRegistrationRequest
    //   3	67	2	localParcel1	android.os.Parcel
    //   7	59	3	localParcel2	android.os.Parcel
    // Exception table:
    //   from	to	target	type
    //   8	14	64	finally
    //   18	29	64	finally
    //   29	47	64	finally
    //   56	61	64	finally
  }
  
  /* Error */
  public void zza(com.google.android.gms.fitness.request.SessionStartRequest paramSessionStartRequest)
  {
    // Byte code:
    //   0: invokestatic 26	android/os/Parcel:obtain	()Landroid/os/Parcel;
    //   3: astore_2
    //   4: invokestatic 26	android/os/Parcel:obtain	()Landroid/os/Parcel;
    //   7: astore_3
    //   8: aload_2
    //   9: ldc 28
    //   11: invokevirtual 32	android/os/Parcel:writeInterfaceToken	(Ljava/lang/String;)V
    //   14: aload_1
    //   15: ifnull +41 -> 56
    //   18: aload_2
    //   19: iconst_1
    //   20: invokevirtual 36	android/os/Parcel:writeInt	(I)V
    //   23: aload_1
    //   24: aload_2
    //   25: iconst_0
    //   26: invokevirtual 66	com/google/android/gms/fitness/request/SessionStartRequest:writeToParcel	(Landroid/os/Parcel;I)V
    //   29: aload_0
    //   30: getfield 15	com/google/android/gms/internal/zzoq$zza$zza:zzoz	Landroid/os/IBinder;
    //   33: iconst_1
    //   34: aload_2
    //   35: aload_3
    //   36: iconst_0
    //   37: invokeinterface 48 5 0
    //   42: pop
    //   43: aload_3
    //   44: invokevirtual 51	android/os/Parcel:readException	()V
    //   47: aload_3
    //   48: invokevirtual 54	android/os/Parcel:recycle	()V
    //   51: aload_2
    //   52: invokevirtual 54	android/os/Parcel:recycle	()V
    //   55: return
    //   56: aload_2
    //   57: iconst_0
    //   58: invokevirtual 36	android/os/Parcel:writeInt	(I)V
    //   61: goto -32 -> 29
    //   64: astore_1
    //   65: aload_3
    //   66: invokevirtual 54	android/os/Parcel:recycle	()V
    //   69: aload_2
    //   70: invokevirtual 54	android/os/Parcel:recycle	()V
    //   73: aload_1
    //   74: athrow
    // Local variable table:
    //   start	length	slot	name	signature
    //   0	75	0	this	zza
    //   0	75	1	paramSessionStartRequest	com.google.android.gms.fitness.request.SessionStartRequest
    //   3	67	2	localParcel1	android.os.Parcel
    //   7	59	3	localParcel2	android.os.Parcel
    // Exception table:
    //   from	to	target	type
    //   8	14	64	finally
    //   18	29	64	finally
    //   29	47	64	finally
    //   56	61	64	finally
  }
  
  /* Error */
  public void zza(com.google.android.gms.fitness.request.SessionStopRequest paramSessionStopRequest)
  {
    // Byte code:
    //   0: invokestatic 26	android/os/Parcel:obtain	()Landroid/os/Parcel;
    //   3: astore_2
    //   4: invokestatic 26	android/os/Parcel:obtain	()Landroid/os/Parcel;
    //   7: astore_3
    //   8: aload_2
    //   9: ldc 28
    //   11: invokevirtual 32	android/os/Parcel:writeInterfaceToken	(Ljava/lang/String;)V
    //   14: aload_1
    //   15: ifnull +41 -> 56
    //   18: aload_2
    //   19: iconst_1
    //   20: invokevirtual 36	android/os/Parcel:writeInt	(I)V
    //   23: aload_1
    //   24: aload_2
    //   25: iconst_0
    //   26: invokevirtual 70	com/google/android/gms/fitness/request/SessionStopRequest:writeToParcel	(Landroid/os/Parcel;I)V
    //   29: aload_0
    //   30: getfield 15	com/google/android/gms/internal/zzoq$zza$zza:zzoz	Landroid/os/IBinder;
    //   33: iconst_2
    //   34: aload_2
    //   35: aload_3
    //   36: iconst_0
    //   37: invokeinterface 48 5 0
    //   42: pop
    //   43: aload_3
    //   44: invokevirtual 51	android/os/Parcel:readException	()V
    //   47: aload_3
    //   48: invokevirtual 54	android/os/Parcel:recycle	()V
    //   51: aload_2
    //   52: invokevirtual 54	android/os/Parcel:recycle	()V
    //   55: return
    //   56: aload_2
    //   57: iconst_0
    //   58: invokevirtual 36	android/os/Parcel:writeInt	(I)V
    //   61: goto -32 -> 29
    //   64: astore_1
    //   65: aload_3
    //   66: invokevirtual 54	android/os/Parcel:recycle	()V
    //   69: aload_2
    //   70: invokevirtual 54	android/os/Parcel:recycle	()V
    //   73: aload_1
    //   74: athrow
    // Local variable table:
    //   start	length	slot	name	signature
    //   0	75	0	this	zza
    //   0	75	1	paramSessionStopRequest	com.google.android.gms.fitness.request.SessionStopRequest
    //   3	67	2	localParcel1	android.os.Parcel
    //   7	59	3	localParcel2	android.os.Parcel
    // Exception table:
    //   from	to	target	type
    //   8	14	64	finally
    //   18	29	64	finally
    //   29	47	64	finally
    //   56	61	64	finally
  }
  
  /* Error */
  public void zza(com.google.android.gms.fitness.request.SessionUnregistrationRequest paramSessionUnregistrationRequest)
  {
    // Byte code:
    //   0: invokestatic 26	android/os/Parcel:obtain	()Landroid/os/Parcel;
    //   3: astore_2
    //   4: invokestatic 26	android/os/Parcel:obtain	()Landroid/os/Parcel;
    //   7: astore_3
    //   8: aload_2
    //   9: ldc 28
    //   11: invokevirtual 32	android/os/Parcel:writeInterfaceToken	(Ljava/lang/String;)V
    //   14: aload_1
    //   15: ifnull +42 -> 57
    //   18: aload_2
    //   19: iconst_1
    //   20: invokevirtual 36	android/os/Parcel:writeInt	(I)V
    //   23: aload_1
    //   24: aload_2
    //   25: iconst_0
    //   26: invokevirtual 74	com/google/android/gms/fitness/request/SessionUnregistrationRequest:writeToParcel	(Landroid/os/Parcel;I)V
    //   29: aload_0
    //   30: getfield 15	com/google/android/gms/internal/zzoq$zza$zza:zzoz	Landroid/os/IBinder;
    //   33: bipush 6
    //   35: aload_2
    //   36: aload_3
    //   37: iconst_0
    //   38: invokeinterface 48 5 0
    //   43: pop
    //   44: aload_3
    //   45: invokevirtual 51	android/os/Parcel:readException	()V
    //   48: aload_3
    //   49: invokevirtual 54	android/os/Parcel:recycle	()V
    //   52: aload_2
    //   53: invokevirtual 54	android/os/Parcel:recycle	()V
    //   56: return
    //   57: aload_2
    //   58: iconst_0
    //   59: invokevirtual 36	android/os/Parcel:writeInt	(I)V
    //   62: goto -33 -> 29
    //   65: astore_1
    //   66: aload_3
    //   67: invokevirtual 54	android/os/Parcel:recycle	()V
    //   70: aload_2
    //   71: invokevirtual 54	android/os/Parcel:recycle	()V
    //   74: aload_1
    //   75: athrow
    // Local variable table:
    //   start	length	slot	name	signature
    //   0	76	0	this	zza
    //   0	76	1	paramSessionUnregistrationRequest	com.google.android.gms.fitness.request.SessionUnregistrationRequest
    //   3	68	2	localParcel1	android.os.Parcel
    //   7	60	3	localParcel2	android.os.Parcel
    // Exception table:
    //   from	to	target	type
    //   8	14	65	finally
    //   18	29	65	finally
    //   29	48	65	finally
    //   57	62	65	finally
  }
}

/* Location:
 * Qualified Name:     com.google.android.gms.internal.zzoq.zza.zza
 * Java Class Version: 6 (50.0)
 * JD-Core Version:    0.7.1
 */